{
    "parameters": {
            "storageAccounts":{
                
                "Value":[
                    {
                        "stgname":"weatherappstg1"
                    },
                    {
                         "stgname":"weatherappstg2"
                    },
                   {
                         "stgname":"weatherappstg3"
                   }
    
        ]
            },
            "env":{
                "value":"qa"
            },
            "skuName": {
                
                "Value":"Standard_LRS"
            },
            "skuTier": {
            "value": "Standard"
             },
            "kvName": {
               
                "Value":"devopskernel2kv"
            },
            "dbSecretName": {
               
                "Value":"DBSecName"
            },
            "dbSecretValue": {
                
                "Value": "password"
            },
            "sqlPassword": {
               
                "Value":"SQLPassword"
            },
            "sqlpasswordValue": {
               
                "value": "password123"
            }
    
    
    
        }
    }