{
    "parameters":{
        "keyvaultname":{
            "value": "weatherappkeyvault"
        },
        "tenantId":{
            "value": "026b8468-803d-4300-8831-bef5b66f82cf"
        },
        "objectId":{
            "value": "c83fca92-09af-411d-bb27-74229b3d819c"
        },
        "secrets":{
            "value":[
                {
                    "secretName":"DataBaseName",
                    "secretValue":"Testvalue1"
                },
                {
                    "secretName":"DataBasePassword",
                    "secretValue":"Testvalue2"
                },
                {
                    "secretName":"DataBaseServerLink",
                    "secretValue":"Testvalue3"
                },
                {
                    "secretName":"DataBaseUserName",
                    "secretValue":"Testvalue4"
                }
            ]
        }
    }
}